freggersbot/__init__.py
freggersbot/__main__.py
freggersbot/freggers.py
freggersbot/animation/__init__.py
freggersbot/animation/movement.py
freggersbot/animation/point2point_movement.py
freggersbot/data/__init__.py
freggersbot/data/action.py
freggersbot/data/animation.py
freggersbot/data/avatar.py
freggersbot/data/chat.py
freggersbot/data/ctxt_room.py
freggersbot/data/ctxt_server.py
freggersbot/data/effect.py
freggersbot/data/env.py
freggersbot/data/interaction.py
freggersbot/data/item.py
freggersbot/data/item_interaction.py
freggersbot/data/item_properties.py
freggersbot/data/list_cmd.py
freggersbot/data/path.py
freggersbot/data/position.py
freggersbot/data/shop_item.py
freggersbot/data/transfer.py
freggersbot/data/vector.py
freggersbot/data/waypoint.py
freggersbot/iso/__init__.py
freggersbot/iso/container.py
freggersbot/iso/iso_star.py
freggersbot/iso/item.py
freggersbot/iso/player.py
freggersbot/iso/wob_registry.py
freggersbot/locale/__init__.py
freggersbot/locale/de.py
freggersbot/locale/en.py
freggersbot/media/__init__.py
freggersbot/media/background.py
freggersbot/media/container_decoder.py
freggersbot/media/decoder.py
freggersbot/media/level.py
freggersbot/media/resource_manager.py
freggersbot/net/__init__.py
freggersbot/net/amf_api.py
freggersbot/net/utf_message.py
freggersbot/utils/__init__.py
freggersbot/utils/bytebuffer.py
freggersbot/utils/item_pickup.py
freggersbot/utils/item_search.py
freggersbot-1.0.47.dist-info/LICENSE
freggersbot-1.0.47.dist-info/METADATA
freggersbot-1.0.47.dist-info/WHEEL
freggersbot-1.0.47.dist-info/top_level.txt
freggersbot-1.0.47.dist-info/RECORD
